odoo10_addon_business_requirement_gap_analysis_task-10.0.1.0.0-py2.7-nspkg.pth
odoo/addons/business_requirement_gap_analysis_task/README.rst
odoo/addons/business_requirement_gap_analysis_task/__init__.py
odoo/addons/business_requirement_gap_analysis_task/__manifest__.py
odoo/addons/business_requirement_gap_analysis_task/data/business_requirement_demo.xml
odoo/addons/business_requirement_gap_analysis_task/data/gap_analysis_task_demo.xml
odoo/addons/business_requirement_gap_analysis_task/models/__init__.py
odoo/addons/business_requirement_gap_analysis_task/models/business.py
odoo/addons/business_requirement_gap_analysis_task/models/res_config.py
odoo/addons/business_requirement_gap_analysis_task/tests/__init__.py
odoo/addons/business_requirement_gap_analysis_task/tests/test_wizard_br.py
odoo/addons/business_requirement_gap_analysis_task/views/business_requirement_gap_analysis_task.xml
odoo/addons/business_requirement_gap_analysis_task/views/res_config.xml
odoo/addons/business_requirement_gap_analysis_task/wizard/__init__.py
odoo/addons/business_requirement_gap_analysis_task/wizard/create_gap_task.py
odoo/addons/business_requirement_gap_analysis_task/wizard/create_gap_task.xml
odoo10_addon_business_requirement_gap_analysis_task-10.0.1.0.0.dist-info/DESCRIPTION.rst
odoo10_addon_business_requirement_gap_analysis_task-10.0.1.0.0.dist-info/METADATA
odoo10_addon_business_requirement_gap_analysis_task-10.0.1.0.0.dist-info/RECORD
odoo10_addon_business_requirement_gap_analysis_task-10.0.1.0.0.dist-info/WHEEL
odoo10_addon_business_requirement_gap_analysis_task-10.0.1.0.0.dist-info/metadata.json
odoo10_addon_business_requirement_gap_analysis_task-10.0.1.0.0.dist-info/namespace_packages.txt
odoo10_addon_business_requirement_gap_analysis_task-10.0.1.0.0.dist-info/top_level.txt
